pysumoapi/__init__.py
pysumoapi/client.py
pysumoapi/models/__init__.py
pysumoapi/models/banzuke.py
pysumoapi/models/basho.py
pysumoapi/models/kimarite.py
pysumoapi/models/kimarite_matches.py
pysumoapi/models/match.py
pysumoapi/models/measurements.py
pysumoapi/models/ranks.py
pysumoapi/models/rikishi.py
pysumoapi/models/rikishi_matches.py
pysumoapi/models/rikishi_stats.py
pysumoapi/models/shikonas.py
pysumoapi/models/torikumi.py
pysumoapi-0.3.0.dist-info/METADATA
pysumoapi-0.3.0.dist-info/WHEEL
pysumoapi-0.3.0.dist-info/licenses/LICENSE
pysumoapi-0.3.0.dist-info/RECORD
