Metadata-Version: 2.4
Name: pysumoapi
Version: 0.3.0
Summary: A Python client library for the Sumo API
Project-URL: Homepage, https://github.com/colebrumley/pysumoapi
Project-URL: Documentation, https://github.com/colebrumley/pysumoapi#readme
Project-URL: Repository, https://github.com/colebrumley/pysumoapi.git
Project-URL: Issues, https://github.com/colebrumley/pysumoapi/issues
Project-URL: Changelog, https://github.com/colebrumley/pysumoapi/blob/main/CHANGELOG.md
Author-email: Cole Brumley <colebrumley@users.noreply.github.com>
Maintainer-email: Cole Brumley <colebrumley@users.noreply.github.com>
License: MIT License
License-File: LICENSE
Keywords: api,japan,sports,sumo,wrestling
Classifier: Development Status :: 4 - Beta
Classifier: Intended Audience :: Developers
Classifier: License :: OSI Approved :: MIT License
Classifier: Programming Language :: Python :: 3
Classifier: Programming Language :: Python :: 3.9
Classifier: Programming Language :: Python :: 3.10
Classifier: Programming Language :: Python :: 3.11
Classifier: Programming Language :: Python :: 3.12
Classifier: Topic :: Software Development :: Libraries :: Python Modules
Requires-Python: >=3.9
Requires-Dist: certifi>=2024.2.0
Requires-Dist: httpx[http2]>=0.24.0
Requires-Dist: pydantic>=2.0.0
Provides-Extra: dev
Requires-Dist: black>=24.2.0; extra == 'dev'
Requires-Dist: build>=1.1.1; extra == 'dev'
Requires-Dist: mypy>=1.8.0; extra == 'dev'
Requires-Dist: pytest-asyncio>=0.26.0; extra == 'dev'
Requires-Dist: pytest-cov>=4.1.0; extra == 'dev'
Requires-Dist: pytest>=8.0.0; extra == 'dev'
Requires-Dist: ruff>=0.2.0; extra == 'dev'
Requires-Dist: twine>=5.0.0; extra == 'dev'
